{
    "count": 4,
    "next": null,
    "previous": null,
    "results": [
        {
            "id": 355,
            "reactions": {
                "approves": 0,
                "disapproves": 0
            },
            "is_mine": false,
            "semester": "",
            "rating": 5,
            "comment": "没有固定教材，课程内容以上课使用的PPT为准，主要参考书为An introduction to language. By Victoria Fromkin, Robert Rodman and Nina Hyams. Tenth Edition。（PPT和书都会上传至网络学堂）本课程的教学目标为了解理论语言学五大核心领域：语音学、音系学、形态学、句法学、语义学，能对自然语言进行简单描写和分析，是理论语言学的入门课程，适合所有对语言学感兴趣的学生。邓老师讲课基础扎实，深入浅出，喜欢互动并鼓励发言，课堂氛围比较活跃，允许同学随时提问。学习任务：每学期3-4次作业，题型均为简答，与课程内容紧密相关，又有⼀定拓展性，每次10分，完成时间为⼀到两周。期末闭卷考试，题型与作业相似，占60-70分（如果考试情况太惨淡，老师会适当增加作业分数占比）。作业和考试中可能出现附加题，完成即有额外奖励分数。学习建议：语言学是⼀种经验科学，比起文学，它更具有“理科”思维，需要⼀定发现问题、总结规律的能力。作业和考试都不要求字数，论述清楚即可。这是⼀门给分客观的课，每次作业都有批改和助教讲解，虽然课程对出勤没有要求，但是仅靠课下看PPT是⼀定学不好的，建议认真听课、写作业，尽量参加每⼀次作业讲解，有问题及时提问，期末考试前再梳理⼀遍PPT，4.0水到渠成。",
            "created_at": "2024/07/21 14:26",
            "modified_at": "2024/07/21 14:26",
            "score": null,
            "moderator_remark": null
        },
        {
            "id": 354,
            "reactions": {
                "approves": 0,
                "disapproves": 0
            },
            "is_mine": false,
            "semester": "",
            "rating": 4,
            "comment": "会给阅读文本参考，但是不强求，只是读了会更好理解上课的内容。老师人非常非常非常好，本课是语言学打基础的课，如果想要学语言学，最好选这门课。而且老师讲的内容非常丰富细致，但是需要同学们花时间背知识点以及理解，多思考，多问问题，老师会耐心解答，上课可以随时提问，下课也可以拉住盾盾问（bushi。给分客观，考多少给多少，但是会有附加分，做出来了多给分，做不出来不扣分，只要认真上课认真复习，拿高分还是没问题的。",
            "created_at": "2024/07/21 14:26",
            "modified_at": "2024/07/21 14:26",
            "score": null,
            "moderator_remark": null
        },
        {
            "id": 353,
            "reactions": {
                "approves": 0,
                "disapproves": 0
            },
            "is_mine": false,
            "semester": "",
            "rating": 5,
            "comment": "（2021春）课程任务量：四次平时作业（一次时限一周）+一次期末考试。老师教学风格：很理工科，强调把具体知识搞懂而非记住概念，考试和作业都是在运用知识。给分不错，但是很客观，考多少、作业分数是多少，最后总评就多少分。课程感悟：上课不认真听，看课件是看不懂的。有疑问可以随时提出，老师会随时解答。",
            "created_at": "2024/07/21 14:26",
            "modified_at": "2024/07/21 14:26",
            "score": null,
            "moderator_remark": null
        },
        {
            "id": 352,
            "reactions": {
                "approves": 0,
                "disapproves": 0
            },
            "is_mine": false,
            "semester": "",
            "rating": 5,
            "comment": "（2019秋）几次课后作业（大概3-4次）+期末考试。是一门需要认真做作业，认真听课，认真复习，认真背知识点才能拿高分的课。老师很授课风格很有趣，讲了语言学的基础知识，认真听收获会很大。",
            "created_at": "2024/07/21 14:25",
            "modified_at": "2024/07/21 14:25",
            "score": null,
            "moderator_remark": null
        }
    ]
}