{
  "count": 1,
  "next": null,
  "previous": null,
  "results": [
    {
      "id": 2373,
      "rating": 5,
      "comment": "考核方式：每次课后的小练习（总共完成7-8次即可）、4次阶段性小作业（都要完成，和刚学完的内容相关）、2个任务型作业（形式每年不一样）、期中10%、期末口语10%、期末笔试40%；考勤需要全勤。\n\n授课质量与给分：非常喜欢Nisi上课，每次西语课是我每周最轻松且最愉悦的时刻之一；课上建议跟紧词汇补充和语法部分，讲的语法一定理解透（不明白的地方问AI或上网查，但总体来说课上讲得很清晰），词汇做好电子或纸质笔记，可用Anki等间隔复习工具辅助背一背。任务量适中，正常完成课程任务即可拿不错的分，语言中心有强制的4.0比例限额，这个没办法。\n\n一些话给想学西语但拿不定选哪一级的小登：西语2其实门槛没有多高，如果你喜欢西语并且通过Duolingo等途径自学过，就可以考虑跳过1直接报2。具体来说：(1)已经掌握西语的发音规则（其实很简单）；(2)下本电子版的『现代西班牙语1』看一眼，前8章的语法点（基本的陈述现在时变位规则）掌握了，且前8章词汇认识50%或以上。如果满足以上两个条件就可以直接试试2。如果没有系统学过命令式、虚拟式不建议直接报3，因为2的重点就是学这两个而且挺有的可学。\n\n点评人：Arch酱\n\n上课学期：25春",
      "created_at": "2025/06/30 23:39",
      "score": "4.0"
    }
  ]
}