{
    "count": 7,
    "next": null,
    "previous": null,
    "results": [
        {
            "id": 701,
            "reactions": {
                "approves": 0,
                "disapproves": 0
            },
            "is_mine": false,
            "semester": "",
            "rating": 4,
            "comment": "每周一节小课同学小组报告，一节小课老师讲课，无压力",
            "created_at": "2024/07/21 17:16",
            "modified_at": "2024/07/21 17:16",
            "score": null,
            "moderator_remark": null
        },
        {
            "id": 700,
            "reactions": {
                "approves": 0,
                "disapproves": 0
            },
            "is_mine": false,
            "semester": "",
            "rating": 5,
            "comment": "虽然是水课，但是老师讲的不枯燥，会夹带一些老师专业心理学的有趣的内容，所以如果讲到感兴趣的内容也可以听一听，平时不留作业，只有期中小作文，课堂展示和期末考试",
            "created_at": "2024/07/21 17:16",
            "modified_at": "2024/07/21 17:16",
            "score": null,
            "moderator_remark": null
        },
        {
            "id": 699,
            "reactions": {
                "approves": 0,
                "disapproves": 0
            },
            "is_mine": false,
            "semester": "",
            "rating": 4,
            "comment": "任务较轻，pre15分钟，期中500字，期末考试两道大题。给分好，强力推荐",
            "created_at": "2024/07/21 17:16",
            "modified_at": "2024/07/21 17:16",
            "score": null,
            "moderator_remark": null
        },
        {
            "id": 698,
            "reactions": {
                "approves": 0,
                "disapproves": 0
            },
            "is_mine": false,
            "semester": "",
            "rating": 4,
            "comment": "每节课有三个小组上去pre，期中有个小作文，期末考试也类似于写作文。美女老师人超好",
            "created_at": "2024/07/21 17:16",
            "modified_at": "2024/07/21 17:16",
            "score": null,
            "moderator_remark": null
        },
        {
            "id": 697,
            "reactions": {
                "approves": 0,
                "disapproves": 0
            },
            "is_mine": false,
            "semester": "",
            "rating": 5,
            "comment": "一个小组展示，一个期中总结，一个期末开卷考试，平时没作业，老师很漂亮。半堂课小组展示，半堂课讲内容",
            "created_at": "2024/07/21 17:16",
            "modified_at": "2024/07/21 17:16",
            "score": null,
            "moderator_remark": null
        },
        {
            "id": 696,
            "reactions": {
                "approves": 0,
                "disapproves": 0
            },
            "is_mine": false,
            "semester": "",
            "rating": 5,
            "comment": "第一小节小组展示，第二小节讲ppt",
            "created_at": "2024/07/21 17:15",
            "modified_at": "2024/07/21 17:15",
            "score": null,
            "moderator_remark": null
        },
        {
            "id": 695,
            "reactions": {
                "approves": 0,
                "disapproves": 0
            },
            "is_mine": false,
            "semester": "",
            "rating": 5,
            "comment": "一学期只用小组合作pre一次+期末开卷考试，剩下的课完全可以躺过去！而且老师超级漂亮！",
            "created_at": "2024/07/21 17:15",
            "modified_at": "2024/07/21 17:15",
            "score": null,
            "moderator_remark": null
        }
    ]
}