{
  "count": 2,
  "next": null,
  "previous": null,
  "results": [
    {
      "id": 318,
      "rating": 5,
      "comment": "老师比较侧重史学理论的讲授，推荐有一定史学理论基础的人学习。主要任务有二，期中pre，期末报告，期中pre主要是围绕学术论文（近几年主要是新清史）；期末报告，有时候期末报告就是对期中报告的完善，但每一年的要求可能略有差别，具体情况仍取决于老师的想法。这门课给分比较严格。学习建议：如果之前不了解史学理论，建议要多了解一下。因为这门课设计上为高年级同学开设，所以其理论味道十分浓厚，一定要多吸取史学理论的知识，不然可能在上课时感到困难。另外，明清史的材料极为丰富庞杂，需要多加小心，仔细辨析。",
      "created_at": "2024/07/21 14:12",
      "score": null
    },
    {
      "id": 317,
      "rating": 5,
      "comment": "（2021春）黄振萍教授面向大三年级开设的断代史课程。课程风格轻松愉悦，与黄教授开设的另两门课非常类似，也有一些内容有重叠。黄教授在讲授中侧重思想史的部分，特别是他本人研究的王阳明思想。明清史课程在介绍史料的基础上主要聚焦于明清史领域中外学界关注的热点话题如：明代儒学、大礼议、锦衣卫以及资本主义萌芽等等。课程作业有期中的书评（包含读书报告与课堂展示），期末的研究综述（根据黄教授的口谕，可以做和明清有关的任何作业，形式不限于研究综述。人物年谱、小论文都可以）。给分非常好，黄教授人也非常好，遇到作业来不及交的情况可以直接顺延。在上课过程中黄教授非常注重同学们思维的训练，会让大家反思如何看待过去、看待历史，选修明清史会对整个中国史学习非常有帮助，五星推荐！",
      "created_at": "2024/07/21 14:11",
      "score": null
    }
  ]
}