{
    "tid": "1231",
    "name": "王红卫",
    "related_courses": [
        {
            "id": 2528,
            "code": "2527",
            "name": "综合课题训练（2）",
            "avg": 0.0,
            "count": 0
        },
        {
            "id": 2620,
            "code": "2619",
            "name": "专业实践",
            "avg": 0.0,
            "count": 0
        },
        {
            "id": 3772,
            "code": "3771",
            "name": "编排设计",
            "avg": 0.0,
            "count": 0
        },
        {
            "id": 7451,
            "code": "7450",
            "name": "字体设计",
            "avg": 0.0,
            "count": 0
        },
        {
            "id": 11909,
            "code": "11910",
            "name": "书籍设计概论",
            "avg": 0.0,
            "count": 0
        },
        {
            "id": 12339,
            "code": "12340",
            "name": "创意字体设计",
            "avg": 0.0,
            "count": 0
        },
        {
            "id": 19473,
            "code": "19494",
            "name": "书籍设计（1）",
            "avg": 0.0,
            "count": 0
        },
        {
            "id": 19603,
            "code": "19626",
            "name": "平面构成",
            "avg": 0.0,
            "count": 0
        },
        {
            "id": 24427,
            "code": "24580",
            "name": "专业实习",
            "avg": 0.0,
            "count": 0
        },
        {
            "id": 32885,
            "code": "33047",
            "name": "社会实践",
            "avg": 0.0,
            "count": 0
        },
        {
            "id": 33891,
            "code": "34053",
            "name": "思政实践",
            "avg": 0.0,
            "count": 0
        },
        {
            "id": 34028,
            "code": "34190",
            "name": "专业考察",
            "avg": 0.0,
            "count": 0
        },
        {
            "id": 34044,
            "code": "34206",
            "name": "综合课题训练（1）",
            "avg": 0.0,
            "count": 0
        },
        {
            "id": 34637,
            "code": "34799",
            "name": "海报设计",
            "avg": 0.0,
            "count": 0
        },
        {
            "id": 1619,
            "code": "1618",
            "name": "书籍设计",
            "avg": 0.0,
            "count": 0
        }
    ]
}