{
    "tid": "1355",
    "name": "罗德胤",
    "related_courses": [
        {
            "id": 5396,
            "code": "5395",
            "name": "建筑设计（2上）",
            "avg": 0.0,
            "count": 0
        },
        {
            "id": 6355,
            "code": "6354",
            "name": "乡土建筑学",
            "avg": 0.0,
            "count": 0
        },
        {
            "id": 8270,
            "code": "8269",
            "name": "乡土建筑与东方主义",
            "avg": 0.0,
            "count": 0
        },
        {
            "id": 8453,
            "code": "8452",
            "name": "建筑设计（1上）",
            "avg": 0.0,
            "count": 0
        },
        {
            "id": 8581,
            "code": "8580",
            "name": "建筑设计（2下）",
            "avg": 0.0,
            "count": 0
        },
        {
            "id": 25988,
            "code": "26150",
            "name": "古建测绘实习",
            "avg": 0.0,
            "count": 0
        },
        {
            "id": 26242,
            "code": "26404",
            "name": "建筑设计（1下）",
            "avg": 0.0,
            "count": 0
        },
        {
            "id": 27915,
            "code": "28077",
            "name": "建筑设计（3上）",
            "avg": 0.0,
            "count": 0
        },
        {
            "id": 31496,
            "code": "31658",
            "name": "设计基础(4)",
            "avg": 0.0,
            "count": 0
        },
        {
            "id": 31622,
            "code": "31784",
            "name": "综合论文训练",
            "avg": 0.0,
            "count": 0
        },
        {
            "id": 33164,
            "code": "33326",
            "name": "设计基础(3)",
            "avg": 0.0,
            "count": 0
        },
        {
            "id": 1850,
            "code": "1849",
            "name": "乡土聚落研究",
            "avg": 0.0,
            "count": 0
        }
    ]
}