{
    "tid": "136",
    "name": "张陶伟",
    "related_courses": [
        {
            "id": 3896,
            "code": "3895",
            "name": "国际金融",
            "avg": 0.0,
            "count": 0
        },
        {
            "id": 5886,
            "code": "5885",
            "name": "国际金融市场",
            "avg": 0.0,
            "count": 0
        },
        {
            "id": 7731,
            "code": "7730",
            "name": "公司金融",
            "avg": 0.0,
            "count": 0
        },
        {
            "id": 18110,
            "code": "18127",
            "name": "投资银行业务",
            "avg": 0.0,
            "count": 0
        },
        {
            "id": 18771,
            "code": "18788",
            "name": "投资学",
            "avg": 0.0,
            "count": 0
        },
        {
            "id": 19629,
            "code": "19652",
            "name": "管理案例研究与分析",
            "avg": 0.0,
            "count": 0
        },
        {
            "id": 22946,
            "code": "23070",
            "name": "外汇业务与市场",
            "avg": 0.0,
            "count": 0
        },
        {
            "id": 28175,
            "code": "28337",
            "name": "金融风险管理",
            "avg": 0.0,
            "count": 0
        },
        {
            "id": 144,
            "code": "143",
            "name": "战略投融资",
            "avg": 0.0,
            "count": 0
        }
    ]
}