{
    "tid": "2050",
    "name": "生安锋",
    "related_courses": [
        {
            "id": 3251,
            "code": "3250",
            "name": "《圣经》与文学",
            "avg": 3.0,
            "count": 1
        },
        {
            "id": 3919,
            "code": "3918",
            "name": "英语戏剧排练与英语朗读",
            "avg": 0.0,
            "count": 0
        },
        {
            "id": 4644,
            "code": "4643",
            "name": "比较文学导论",
            "avg": 0.0,
            "count": 0
        },
        {
            "id": 7376,
            "code": "7375",
            "name": "英语精读(1)",
            "avg": 0.0,
            "count": 0
        },
        {
            "id": 8860,
            "code": "8859",
            "name": "英语精读(2)",
            "avg": 0.0,
            "count": 0
        },
        {
            "id": 10226,
            "code": "10226",
            "name": "新历史主义文学理论",
            "avg": 0.0,
            "count": 0
        },
        {
            "id": 13741,
            "code": "13749",
            "name": "综合英语(1)",
            "avg": 0.0,
            "count": 0
        },
        {
            "id": 13806,
            "code": "13814",
            "name": "综合英语(2)",
            "avg": 0.0,
            "count": 0
        },
        {
            "id": 17406,
            "code": "17423",
            "name": "英语写作(4)",
            "avg": 0.0,
            "count": 0
        },
        {
            "id": 17525,
            "code": "17542",
            "name": "英语写作(3)",
            "avg": 0.0,
            "count": 0
        },
        {
            "id": 17580,
            "code": "17597",
            "name": "英语听力(1)",
            "avg": 0.0,
            "count": 0
        },
        {
            "id": 19741,
            "code": "19765",
            "name": "大学英语读写译(1)",
            "avg": 0.0,
            "count": 0
        },
        {
            "id": 19815,
            "code": "19839",
            "name": "大学英语读写译(3)",
            "avg": 0.0,
            "count": 0
        },
        {
            "id": 20158,
            "code": "20182",
            "name": "英语(2)",
            "avg": 0.0,
            "count": 0
        },
        {
            "id": 20737,
            "code": "20762",
            "name": "综合英语(3)",
            "avg": 0.0,
            "count": 0
        },
        {
            "id": 20868,
            "code": "20893",
            "name": "英语听力(2)",
            "avg": 0.0,
            "count": 0
        },
        {
            "id": 20878,
            "code": "20903",
            "name": "综合英语(4)",
            "avg": 0.0,
            "count": 0
        },
        {
            "id": 21612,
            "code": "21637",
            "name": "英语（第一外国语）",
            "avg": 0.0,
            "count": 0
        },
        {
            "id": 22090,
            "code": "22196",
            "name": "大学英语读写译(2)",
            "avg": 0.0,
            "count": 0
        },
        {
            "id": 22188,
            "code": "22303",
            "name": "英语(1)",
            "avg": 0.0,
            "count": 0
        },
        {
            "id": 23630,
            "code": "23760",
            "name": "综合英语（3）",
            "avg": 0.0,
            "count": 0
        },
        {
            "id": 24551,
            "code": "24704",
            "name": "大一外语强化训练",
            "avg": 0.0,
            "count": 0
        },
        {
            "id": 25662,
            "code": "25823",
            "name": "英语高级听力",
            "avg": 0.0,
            "count": 0
        },
        {
            "id": 26636,
            "code": "26798",
            "name": "西方文论（1）",
            "avg": 0.0,
            "count": 0
        },
        {
            "id": 27379,
            "code": "27541",
            "name": "西方文论（2）",
            "avg": 0.0,
            "count": 0
        },
        {
            "id": 28803,
            "code": "28965",
            "name": "当代西方学术前沿专题讲座",
            "avg": 0.0,
            "count": 0
        },
        {
            "id": 32844,
            "code": "33006",
            "name": "教育博士英语",
            "avg": 0.0,
            "count": 0
        },
        {
            "id": 3240,
            "code": "3239",
            "name": "美国文学",
            "avg": 4.0,
            "count": 1
        }
    ]
}