{
    "tid": "2369",
    "name": "刘锋",
    "related_courses": [
        {
            "id": 8903,
            "code": "8902",
            "name": "工程博弈论",
            "avg": 0.0,
            "count": 0
        },
        {
            "id": 31600,
            "code": "31762",
            "name": "信号、系统与控制",
            "avg": 0.0,
            "count": 0
        },
        {
            "id": 4125,
            "code": "4124",
            "name": "电气工程专业英语实践",
            "avg": 0.0,
            "count": 0
        }
    ]
}