{
    "tid": "2423",
    "name": "宋健",
    "related_courses": [
        {
            "id": 6230,
            "code": "6229",
            "name": "信号与系统（英）",
            "avg": 0.0,
            "count": 0
        },
        {
            "id": 9229,
            "code": "9228",
            "name": "汽车动力学",
            "avg": 0.0,
            "count": 0
        },
        {
            "id": 10842,
            "code": "10843",
            "name": "通信网络设计实例研究",
            "avg": 0.0,
            "count": 0
        },
        {
            "id": 28661,
            "code": "28823",
            "name": "通信系统",
            "avg": 0.0,
            "count": 0
        },
        {
            "id": 4275,
            "code": "4274",
            "name": "汽车理论",
            "avg": 0.0,
            "count": 0
        }
    ]
}