{
    "tid": "244",
    "name": "杨瑞东",
    "related_courses": [
        {
            "id": 336,
            "code": "335",
            "name": "职业能力拓展训练",
            "avg": 0.0,
            "count": 0
        },
        {
            "id": 7263,
            "code": "7262",
            "name": "国学易经与科学决策",
            "avg": 0.0,
            "count": 0
        },
        {
            "id": 273,
            "code": "272",
            "name": "社会工作能力与创新领导力",
            "avg": 0.0,
            "count": 0
        }
    ]
}