{
    "tid": "2445",
    "name": "吴娟",
    "related_courses": [
        {
            "id": 7398,
            "code": "7397",
            "name": "基础梵语(1)",
            "avg": 0.0,
            "count": 0
        },
        {
            "id": 8104,
            "code": "8103",
            "name": "基础梵语（2）",
            "avg": 0.0,
            "count": 0
        },
        {
            "id": 24892,
            "code": "25052",
            "name": "佛经翻译文献导论",
            "avg": 0.0,
            "count": 0
        },
        {
            "id": 25225,
            "code": "25385",
            "name": "中国文化与社会",
            "avg": 0.0,
            "count": 0
        },
        {
            "id": 26017,
            "code": "26179",
            "name": "暑期外语训练",
            "avg": 0.0,
            "count": 0
        },
        {
            "id": 28895,
            "code": "29057",
            "name": "基础巴利语（上）",
            "avg": 0.0,
            "count": 0
        },
        {
            "id": 29510,
            "code": "29672",
            "name": "基础梵语",
            "avg": 0.0,
            "count": 0
        },
        {
            "id": 4331,
            "code": "4330",
            "name": "南亚文学专题研究",
            "avg": 0.0,
            "count": 0
        }
    ]
}