{
    "tid": "2646",
    "name": "鲍捷",
    "related_courses": [
        {
            "id": 5371,
            "code": "5370",
            "name": "纳米技术与智能感知",
            "avg": 0.0,
            "count": 0
        },
        {
            "id": 10064,
            "code": "10063",
            "name": "电子工程及其他领域中的化学",
            "avg": 0.0,
            "count": 0
        },
        {
            "id": 4957,
            "code": "4956",
            "name": "前沿科技与商业化",
            "avg": 0.0,
            "count": 0
        }
    ]
}