{
    "tid": "2667",
    "name": "吴宝森",
    "related_courses": [
        {
            "id": 12859,
            "code": "12862",
            "name": "线性代数(1)",
            "avg": 0.0,
            "count": 0
        },
        {
            "id": 27275,
            "code": "27437",
            "name": "代数几何2",
            "avg": 0.0,
            "count": 0
        },
        {
            "id": 27812,
            "code": "27974",
            "name": "高等线性代数(1)",
            "avg": 0.0,
            "count": 0
        },
        {
            "id": 31448,
            "code": "31610",
            "name": "高等线性代数(2)",
            "avg": 0.0,
            "count": 0
        },
        {
            "id": 34243,
            "code": "34405",
            "name": "几何与对称",
            "avg": 0.0,
            "count": 0
        },
        {
            "id": 5012,
            "code": "5011",
            "name": "黎曼曲面",
            "avg": 0.0,
            "count": 0
        }
    ]
}