{
    "tid": "355",
    "name": "王晓浩",
    "related_courses": [
        {
            "id": 835,
            "code": "834",
            "name": "科学仪器",
            "avg": 0.0,
            "count": 0
        },
        {
            "id": 6049,
            "code": "6048",
            "name": "微传感器",
            "avg": 0.0,
            "count": 0
        },
        {
            "id": 7404,
            "code": "7403",
            "name": "微机电系统技术",
            "avg": 0.0,
            "count": 0
        },
        {
            "id": 10100,
            "code": "10099",
            "name": "工程领域学科前沿讲座",
            "avg": 0.0,
            "count": 0
        },
        {
            "id": 11815,
            "code": "11816",
            "name": "微机电系统技术及应用",
            "avg": 0.0,
            "count": 0
        },
        {
            "id": 13508,
            "code": "13516",
            "name": "微机电器件与系统",
            "avg": 0.0,
            "count": 0
        },
        {
            "id": 24382,
            "code": "24535",
            "name": "微机电器件设计与仿真实验",
            "avg": 0.0,
            "count": 0
        },
        {
            "id": 28236,
            "code": "28398",
            "name": "仪器行业",
            "avg": 0.0,
            "count": 0
        },
        {
            "id": 28943,
            "code": "29105",
            "name": "工程测量系统",
            "avg": 0.0,
            "count": 0
        },
        {
            "id": 407,
            "code": "406",
            "name": "MEMS及其应用",
            "avg": 0.0,
            "count": 0
        }
    ]
}