{
    "tid": "4232",
    "name": "Aaron Crippen",
    "related_courses": [
        {
            "id": 13792,
            "code": "13800",
            "name": "英语写作(4)",
            "avg": 0.0,
            "count": 0
        },
        {
            "id": 14533,
            "code": "14541",
            "name": "英文诗歌赏析",
            "avg": 0.0,
            "count": 0
        },
        {
            "id": 14544,
            "code": "14552",
            "name": "高级英语：美国文学广场",
            "avg": 0.0,
            "count": 0
        },
        {
            "id": 15213,
            "code": "15221",
            "name": "英语散文赏析",
            "avg": 0.0,
            "count": 0
        },
        {
            "id": 15446,
            "code": "15454",
            "name": "英语（第一外国语）",
            "avg": 0.0,
            "count": 0
        },
        {
            "id": 16093,
            "code": "16102",
            "name": "英语写作(3)",
            "avg": 0.0,
            "count": 0
        },
        {
            "id": 16678,
            "code": "16695",
            "name": "实用英语交际技巧",
            "avg": 0.0,
            "count": 0
        },
        {
            "id": 19367,
            "code": "19388",
            "name": "大学英语读写译(3)",
            "avg": 0.0,
            "count": 0
        },
        {
            "id": 13710,
            "code": "13718",
            "name": "世界文学",
            "avg": 0.0,
            "count": 0
        }
    ]
}