{
    "tid": "4687",
    "name": "Richard Shelley",
    "related_courses": [
        {
            "id": 16962,
            "code": "16979",
            "name": "科学史",
            "avg": 0.0,
            "count": 0
        },
        {
            "id": 17031,
            "code": "17048",
            "name": "英语听说(2)",
            "avg": 0.0,
            "count": 0
        },
        {
            "id": 17038,
            "code": "17055",
            "name": "英语听说(3)",
            "avg": 0.0,
            "count": 0
        },
        {
            "id": 19664,
            "code": "19688",
            "name": "英语高级口语",
            "avg": 0.0,
            "count": 0
        },
        {
            "id": 20008,
            "code": "20032",
            "name": "英语听说(1)",
            "avg": 0.0,
            "count": 0
        },
        {
            "id": 24341,
            "code": "24493",
            "name": "大一外语强化训练",
            "avg": 0.0,
            "count": 0
        },
        {
            "id": 16760,
            "code": "16777",
            "name": "技术与社会",
            "avg": 0.0,
            "count": 0
        }
    ]
}