{
    "tid": "4850",
    "name": "王俊杰",
    "related_courses": [
        {
            "id": 17831,
            "code": "17848",
            "name": "检测技术系列实验(1)",
            "avg": 0.0,
            "count": 0
        },
        {
            "id": 18661,
            "code": "18678",
            "name": "控制网络及现场总线",
            "avg": 0.0,
            "count": 0
        },
        {
            "id": 19939,
            "code": "19963",
            "name": "检测原理",
            "avg": 0.0,
            "count": 0
        },
        {
            "id": 28641,
            "code": "28803",
            "name": "卓越工程师培养：因材施教研讨课(4)",
            "avg": 0.0,
            "count": 0
        },
        {
            "id": 29408,
            "code": "29570",
            "name": "卓越工程师培养：因材施教研讨课(1)",
            "avg": 0.0,
            "count": 0
        },
        {
            "id": 30084,
            "code": "30246",
            "name": "卓越工程师培养：因材施教研讨课(2)",
            "avg": 0.0,
            "count": 0
        },
        {
            "id": 30708,
            "code": "30870",
            "name": "卓越工程师培养：因材施教研讨课(3)",
            "avg": 0.0,
            "count": 0
        },
        {
            "id": 32469,
            "code": "32631",
            "name": "建筑材料实验",
            "avg": 0.0,
            "count": 0
        },
        {
            "id": 17590,
            "code": "17607",
            "name": "检测技术系列实验(2)",
            "avg": 0.0,
            "count": 0
        }
    ]
}