{
    "tid": "7115",
    "name": "张元哲",
    "related_courses": [
        {
            "id": 32129,
            "code": "32291",
            "name": "社会调查",
            "avg": 0.0,
            "count": 0
        },
        {
            "id": 32251,
            "code": "32413",
            "name": "党的知识概论",
            "avg": 0.0,
            "count": 0
        },
        {
            "id": 33953,
            "code": "34115",
            "name": "思政实践",
            "avg": 0.0,
            "count": 0
        },
        {
            "id": 32108,
            "code": "32270",
            "name": "国家机关、国际组织实习",
            "avg": 0.0,
            "count": 0
        }
    ]
}