{
    "tid": "7188",
    "name": "Peter Bus",
    "related_courses": [
        {
            "id": 33571,
            "code": "33733",
            "name": "未来人居计算性设计",
            "avg": 0.0,
            "count": 0
        },
        {
            "id": 33572,
            "code": "33734",
            "name": "扩展现实与人工智能驱动的建筑生成方法",
            "avg": 0.0,
            "count": 0
        },
        {
            "id": 32808,
            "code": "32970",
            "name": "设计专题一",
            "avg": 0.0,
            "count": 0
        }
    ]
}