{
    "tid": "889",
    "name": "彭凯平",
    "related_courses": [
        {
            "id": 1133,
            "code": "1132",
            "name": "社会心理学专题研究",
            "avg": 0.0,
            "count": 0
        },
        {
            "id": 5242,
            "code": "5241",
            "name": "数据思维与行为",
            "avg": 0.0,
            "count": 0
        },
        {
            "id": 6804,
            "code": "6803",
            "name": "心理学概论",
            "avg": 0.0,
            "count": 0
        },
        {
            "id": 6805,
            "code": "6804",
            "name": "心理测量学",
            "avg": 0.0,
            "count": 0
        },
        {
            "id": 7897,
            "code": "7896",
            "name": "现代心理学前沿问题选讲",
            "avg": 0.0,
            "count": 0
        },
        {
            "id": 8033,
            "code": "8032",
            "name": "社会与文化心理学研究",
            "avg": 0.0,
            "count": 0
        },
        {
            "id": 8746,
            "code": "8745",
            "name": "积极心理学",
            "avg": 0.0,
            "count": 0
        },
        {
            "id": 8922,
            "code": "8921",
            "name": "心理学专题讲座",
            "avg": 0.0,
            "count": 0
        },
        {
            "id": 9043,
            "code": "9042",
            "name": "跨文化沟通（英）",
            "avg": 0.0,
            "count": 0
        },
        {
            "id": 10362,
            "code": "10363",
            "name": "文化心理学",
            "avg": 0.0,
            "count": 0
        },
        {
            "id": 12519,
            "code": "12522",
            "name": "跨文化沟通",
            "avg": 0.0,
            "count": 0
        },
        {
            "id": 12671,
            "code": "12674",
            "name": "管理心理学",
            "avg": 0.0,
            "count": 0
        },
        {
            "id": 12995,
            "code": "13001",
            "name": "应用心理专业外语",
            "avg": 0.0,
            "count": 0
        },
        {
            "id": 13000,
            "code": "13006",
            "name": "全球领导心理学",
            "avg": 0.0,
            "count": 0
        },
        {
            "id": 14739,
            "code": "14747",
            "name": "心理学史",
            "avg": 0.0,
            "count": 0
        },
        {
            "id": 17919,
            "code": "17936",
            "name": "行为研究的实验方法",
            "avg": 0.0,
            "count": 0
        },
        {
            "id": 27049,
            "code": "27211",
            "name": "社会心理学",
            "avg": 0.0,
            "count": 0
        },
        {
            "id": 28905,
            "code": "29067",
            "name": "应用社会心理学专题",
            "avg": 0.0,
            "count": 0
        },
        {
            "id": 29167,
            "code": "29329",
            "name": "积极心理和人生意义",
            "avg": 0.0,
            "count": 0
        },
        {
            "id": 32541,
            "code": "32703",
            "name": "前沿创新研究：心理健康(1)",
            "avg": 0.0,
            "count": 0
        },
        {
            "id": 33438,
            "code": "33600",
            "name": "全球领导力心理学",
            "avg": 0.0,
            "count": 0
        },
        {
            "id": 1130,
            "code": "1129",
            "name": "心理学理论前沿动态",
            "avg": 0.0,
            "count": 0
        }
    ]
}