{
    "tid": "3429",
    "name": "贺艳兵",
    "related_courses": [
        {
            "id": 10273,
            "code": "10273",
            "name": "材料分析与表征",
            "avg": 0.0,
            "count": 0
        },
        {
            "id": 29733,
            "code": "29895",
            "name": "固态离子学",
            "avg": 0.0,
            "count": 0
        },
        {
            "id": 8936,
            "code": "8935",
            "name": "低碳经济与低碳技术",
            "avg": 0.0,
            "count": 0
        }
    ]
}