{
    "tid": "3733",
    "name": "罗嵘",
    "related_courses": [
        {
            "id": 11309,
            "code": "11310",
            "name": "数字逻辑与处理器基础",
            "avg": 0.0,
            "count": 0
        },
        {
            "id": 13948,
            "code": "13956",
            "name": "数字逻辑电路",
            "avg": 0.0,
            "count": 0
        },
        {
            "id": 13950,
            "code": "13958",
            "name": "数字逻辑设计",
            "avg": 0.0,
            "count": 0
        },
        {
            "id": 22964,
            "code": "23088",
            "name": "逻辑设计与数字系统",
            "avg": 0.0,
            "count": 0
        },
        {
            "id": 10829,
            "code": "10830",
            "name": "数字系统设计",
            "avg": 0.0,
            "count": 0
        }
    ]
}