{
    "tid": "395",
    "name": "MAO SHUDE",
    "related_courses": [
        {
            "id": 6284,
            "code": "6283",
            "name": "漫游在物理和天文的交叉领域",
            "avg": 5.0,
            "count": 2
        },
        {
            "id": 26060,
            "code": "26222",
            "name": "天问：宇宙之美",
            "avg": 5.0,
            "count": 1
        },
        {
            "id": 947,
            "code": "946",
            "name": "星系动力学",
            "avg": 0.0,
            "count": 0
        },
        {
            "id": 449,
            "code": "448",
            "name": "天体物理前沿讲座",
            "avg": 0.0,
            "count": 0
        }
    ]
}