{
    "tid": "6094",
    "name": "刘胜利",
    "related_courses": [
        {
            "id": 25477,
            "code": "25638",
            "name": "科学革命名著选读",
            "avg": 0.0,
            "count": 0
        },
        {
            "id": 27393,
            "code": "27555",
            "name": "现象学科技哲学原著选读",
            "avg": 0.0,
            "count": 0
        },
        {
            "id": 25198,
            "code": "25358",
            "name": "西方科学史名著选读",
            "avg": 0.0,
            "count": 0
        }
    ]
}