{
    "tid": "6743",
    "name": "张文鹏",
    "related_courses": [
        {
            "id": 30933,
            "code": "31095",
            "name": "质谱仪器技术与应用",
            "avg": 0.0,
            "count": 0
        },
        {
            "id": 33186,
            "code": "33348",
            "name": "有机化学与生物化学",
            "avg": 0.0,
            "count": 0
        },
        {
            "id": 29874,
            "code": "30036",
            "name": "有机化学与生物学导论",
            "avg": 0.0,
            "count": 0
        }
    ]
}