{
    "tid": "6773",
    "name": "孙月",
    "related_courses": [
        {
            "id": 34034,
            "code": "34196",
            "name": "综合课题训练（2）",
            "avg": 0.0,
            "count": 0
        },
        {
            "id": 34039,
            "code": "34201",
            "name": "专业实践",
            "avg": 0.0,
            "count": 0
        },
        {
            "id": 34366,
            "code": "34528",
            "name": "传统陶艺（1）",
            "avg": 0.0,
            "count": 0
        },
        {
            "id": 34468,
            "code": "34630",
            "name": "传统陶艺概论",
            "avg": 0.0,
            "count": 0
        },
        {
            "id": 30052,
            "code": "30214",
            "name": "综合造型基础（1）",
            "avg": 0.0,
            "count": 0
        }
    ]
}