{
    "tid": "830",
    "name": "刘宝碇",
    "related_courses": [
        {
            "id": 4712,
            "code": "4711",
            "name": "不确定规划",
            "avg": 0.0,
            "count": 0
        },
        {
            "id": 14048,
            "code": "14056",
            "name": "大学数学(1)(社科类)",
            "avg": 0.0,
            "count": 0
        },
        {
            "id": 14864,
            "code": "14872",
            "name": "数学规划",
            "avg": 0.0,
            "count": 0
        },
        {
            "id": 18227,
            "code": "18244",
            "name": "多层规划",
            "avg": 0.0,
            "count": 0
        },
        {
            "id": 1046,
            "code": "1045",
            "name": "不确定系统",
            "avg": 0.0,
            "count": 0
        }
    ]
}